[
  {
    "lang": "English",
    "media-play": "Play",
    "media-stop": "Stop",
    "media-next": "Next song",
    "media-previous": "Previous song",
    "media-pause": "Pause",
    "media-repeat": "Repeat",
    "media-shuffle": "Shuffle",
    "sound-mute": "Mute",
    "sound-louder": "Louder",
    "sound-quieter": "Quieter",
    "edit": "Edit",
    "search-placeholder": "Search for artists, playlists, ...",
    "search-results": "Results for",
    "song": "Song",
    "songs": "Songs",
    "song-duration": "Duration",
    "artist": "Artist",
    "artists": "Artists",
    "album": "Album",
    "albums": "Albums",
    "album-by": "Album by",
    "album-cover": "Cover",
    "album-information": "Album information",
    "playlist": "Playlist",
    "playlists": "Playlists",
    "playlist-information": "Playlist information",
    "room": "Room",
    "rooms": "Rooms",
    "room-living-room": "Living room",
    "room-bedroom": "Bedroom",
    "room-bedroom-guests": "Guest bedroom",
    "room-kitchen": "Kitchen",
    "room-bath": "Bathroom",
    "room-outdoor": "Garden",
    "room-combined": "Bedroom + Guest bedroom",
    "settings": "Settings",
    "settings-privacy": "Privacy settings",
    "settings-account": "Your Account",
    "settings-system": "System",
    "settings-app": "App settings",
    "settings-legal": "Legal information",
    "menu-my-sonos": "My Sonos",
    "menu-recently-played": "Recently played",
    "menu-artists": "Artists",
    "menu-albums": "Albums",
    "menu-playlists": "Playlists",
    "menu-liked-songs": "Liked Songs",
    "menu-recently-searched": "Recently searched",
    "menu-discover": "Discover",
    "menu-library": "Your Library",
    "menu-spotify": "Spotify",
    "menu-apple-music": "Apple Music",
    "menu-radio": "Radio",
    "menu-podcasts": "Podcasts",
    "menu-recommendations": "Recommendations",
    "button-sonos-add": "Add Sonos",
    "button-sonos-remove": "Remove Sonos",
    "button-stream": "Start playing",
    "button-stream-playlist": "Play on Sonos ...",
    "button-connect-services": "Connect more services",
    "sonos-control-center": "Sonos Control Center",
    "sonos-control-center-text": "The Sonos Control Center lets you connect and disconnect your devices as you like. Simply drag the device to the desired position.",
    "sonos-model-one-sl": "Sonos One SL",
    "sonos-model-one": "Sonos One",
    "sonos-model-five": "Sonos Five"
  },
  {
    "lang": "Deutsch",
    "media-play": "abspielen",
    "media-stop": "Stop",
    "media-next": "N\u00e4chstes Lied",
    "media-previous": "Vorheriges Lied",
    "media-pause": "Pause",
    "media-repeat": "Wiederholen",
    "media-shuffle": "Mischen",
    "sound-mute": "Stumm",
    "sound-louder": "Lauter",
    "sound-quieter": "Leiser",
    "edit": "Bearbeiten",
    "search-placeholder": "Suche nach K\u00fcnstler, Playlisten...",
    "search-results": "Ergebnisse f\u00fcr",
    "song": "Song",
    "songs": "Songs",
    "song-duration": "Dauer",
    "artist": "K\u00fcnstler",
    "artists": "K\u00fcnstler",
    "album": "Album",
    "albums": "Alben",
    "album-by": "Album von",
    "album-cover": "Cover",
    "album-information": "Informationen \u00fcber das Album",
    "playlist": "Playlist",
    "playlists": "Playlisten",
    "playlist-information": "Playlist-Informationen",
    "room": "Zimmer",
    "rooms": "R\u00e4ume",
    "room-living-room": "Wohnzimmer",
    "room-bedroom": "Schlafzimmer",
    "room-bedroom-guests": "G\u00e4stezimmer",
    "room-kitchen": "K\u00fcche",
    "room-bath": "Bad",
    "room-outdoor": "Garten",
    "room-combined": "Schlafzimmer + G\u00e4stezimmer",
    "settings": "Einstellungen",
    "settings-privacy": "Datenschutzeinstellungen",
    "settings-account": "Ihr Konto",
    "settings-system": "System",
    "settings-app": "App Einstellungen",
    "settings-legal": "Rechtsinformation",
    "menu-my-sonos": "Mein Sonos",
    "menu-recently-played": "Letzte Wiedergaben",
    "menu-artists": "K\u00fcnstler",
    "menu-albums": "Alben",
    "menu-playlists": "Wiedergabelisten",
    "menu-liked-songs": "Gespeicherte Songs",
    "menu-recently-searched": "K\u00fcrzlich gesucht",
    "menu-discover": "Entdecken",
    "menu-library": "Ihre Bibliothek",
    "menu-spotify": "Spotify",
    "menu-apple-music": "Apple Music",
    "menu-radio": "Radio",
    "menu-podcasts": "Podcasts",
    "menu-recommendations": "Empfehlungen",
    "button-sonos-add": "Sonos hinzuf\u00fcgen",
    "button-sonos-remove": "Sonos entkoppeln",
    "button-stream": "Musik ausw\u00e4hlen",
    "button-stream-playlist": "Auf Sonos abspielen ...",
    "button-connect-services": "Verbinde weitere Dienste",
    "sonos-control-center": "Sonos Control Center",
    "sonos-control-center-text": "Im Sonos Control Center kannst du deine Ger\u00e4te beliebig miteinander verkn\u00fcpfen oder wieder voneinander trennen. Ziehe das Ger\u00e4t daf\u00fcr einfach an die gew\u00fcnschte Position.",
    "sonos-model-one-sl": "Sonos One SL",
    "sonos-model-one": "Sonos One",
    "sonos-model-five": "Sonos Five"
  },
  {
    "lang": "\u0420\u0443\u0441\u0441\u043a\u0438\u0439",
    "media-play": "\u0418\u0433\u0440\u0430\u0442\u044c",
    "media-stop": "\u0421\u0442\u043e\u043f",
    "media-next": "\u0421\u043b\u0435\u0434\u0443\u044e\u0449\u0430\u044f \u043f\u0435\u0441\u043d\u044f",
    "media-previous": "\u041f\u0440\u0435\u0434\u044b\u0434\u0443\u0449\u0430\u044f \u043f\u0435\u0441\u043d\u044f",
    "media-pause": "\u041f\u0430\u0443\u0437\u0430",
    "media-repeat": "\u041f\u043e\u0432\u0442\u043e\u0440\u0435\u043d\u0438\u0435",
    "media-shuffle": "\u0448\u0430\u0440\u043a\u0430\u043d\u044c\u0435",
    "sound-mute": "\u0431\u0435\u0437\u0433\u043b\u0430\u0441\u043d\u044b\u0439",
    "sound-louder": "\u0413\u0440\u043e\u043c\u0447\u0435",
    "sound-quieter": "\u0422\u0438\u0448\u0435",
    "edit": "\u0440\u0435\u0434\u0430\u043a\u0442\u0438\u0440\u043e\u0432\u0430\u0442\u044c",
    "search-placeholder": "\u041f\u043e\u0438\u0441\u043a \u0438\u0441\u043f\u043e\u043b\u043d\u0438\u0442\u0435\u043b\u0435\u0439, \u043f\u043b\u0435\u0439\u043b\u0438\u0441\u0442\u044b, ...",
    "search-results": "\u0420\u0435\u0437\u0443\u043b\u044c\u0442\u0430\u0442\u044b \u043f\u043e\u0438\u0441\u043a\u0430 \u043f\u043e \u0437\u0430\u043f\u0440\u043e\u0441\u0443",
    "song": "\u043f\u0435\u0441\u043d\u044f",
    "songs": "\u043f\u0435\u0441\u043d\u0438",
    "song-duration": "\u043f\u0440\u043e\u0434\u043e\u043b\u0436\u0438\u0442\u0435\u043b\u044c\u043d\u043e\u0441\u0442\u044c",
    "artist": "\u0445\u0443\u0434\u043e\u0436\u043d\u0438\u043a",
    "artists": "\u0425\u0443\u0434\u043e\u0436\u043d\u0438\u043a\u0438",
    "album": "\u0410\u043b\u044c\u0431\u043e\u043c",
    "albums": "\u0410\u043b\u044c\u0431\u043e\u043c\u044b",
    "album-by": "\u0410\u043b\u044c\u0431\u043e\u043c \u043f\u043e",
    "album-cover": "\u041e\u0431\u043b\u043e\u0436\u043a\u0430",
    "album-information": "\u0438\u043d\u0444\u043e\u0440\u043c\u0430\u0446\u0438\u044f \u043e\u0431 \u0430\u043b\u044c\u0431\u043e\u043c\u0435",
    "playlist": "\u041f\u043b\u0435\u0439\u043b\u0438\u0441\u0442",
    "playlists": "\u041f\u043b\u0435\u0439\u043b\u0438\u0441\u0442\u044b",
    "playlist-information": "\u0438\u043d\u0444\u043e\u0440\u043c\u0430\u0446\u0438\u044f \u043e \u0441\u043f\u0438\u0441\u043a\u0435 \u0432\u043e\u0441\u043f\u0440\u043e\u0438\u0437\u0432\u0435\u0434\u0435\u043d\u0438\u044f",
    "room": "\u041a\u043e\u043c\u043d\u0430\u0442\u0430",
    "rooms": "\u041d\u043e\u043c\u0435\u0440\u0430",
    "room-living-room": "\u0413\u043e\u0441\u0442\u0438\u043d\u0430\u044f",
    "room-bedroom": "\u0441\u043f\u0430\u043b\u044c\u043d\u0430\u044f \u043a\u043e\u043c\u043d\u0430\u0442\u0430",
    "room-bedroom-guests": "\u0413\u043e\u0441\u0442\u0435\u0432\u0430\u044f \u0441\u043f\u0430\u043b\u044c\u043d\u044f",
    "room-kitchen": "\u041a\u0443\u0445\u043d\u044f",
    "room-bath": "\u0432\u0430\u043d\u043d\u0430\u044f \u043a\u043e\u043c\u043d\u0430\u0442\u0430",
    "room-outdoor": "\u0421\u0430\u0434",
    "room-combined": "\u0421\u043f\u0430\u043b\u044c\u043d\u044f + \u0413\u043e\u0441\u0442\u0435\u0432\u0430\u044f \u0441\u043f\u0430\u043b\u044c\u043d\u044f",
    "settings": "\u043d\u0430\u0441\u0442\u0440\u043e\u0439\u043a\u0438",
    "settings-privacy": "\u041d\u0430\u0441\u0442\u0440\u043e\u0439\u043a\u0438 \u043a\u043e\u043d\u0444\u0438\u0434\u0435\u043d\u0446\u0438\u0430\u043b\u044c\u043d\u043e\u0441\u0442\u0438",
    "settings-account": "\u0412\u0430\u0448 \u0441\u0447\u0435\u0442",
    "settings-system": "\u0441\u0438\u0441\u0442\u0435\u043c\u0430",
    "settings-app": "\u043d\u0430\u0441\u0442\u0440\u043e\u0439\u043a\u0438 \u043f\u0440\u0438\u043b\u043e\u0436\u0435\u043d\u0438\u044f",
    "settings-legal": "\u041b\u0435\u0433\u0430\u043b\u044c\u043d\u0430\u044f \u0438\u043d\u0444\u043e\u0440\u043c\u0430\u0446\u0438\u044f",
    "menu-my-sonos": "\u041c\u043e\u0439 Sonos",
    "menu-recently-played": "\u041d\u0435\u0434\u0430\u0432\u043d\u043e \u0432\u043e\u0441\u043f\u0440\u043e\u0438\u0437\u0432\u0435\u0434\u0435\u043d\u043d\u044b\u0435",
    "menu-artists": "\u0425\u0443\u0434\u043e\u0436\u043d\u0438\u043a\u0438",
    "menu-albums": "\u0410\u043b\u044c\u0431\u043e\u043c\u044b",
    "menu-playlists": "\u041f\u043b\u0435\u0439\u043b\u0438\u0441\u0442\u044b",
    "menu-liked-songs": "\u041f\u043e\u043d\u0440\u0430\u0432\u0438\u043b\u0441\u044f \u043f\u0435\u0441\u043d\u044f",
    "menu-recently-searched": "\u041d\u0435\u0434\u0430\u0432\u043d\u043e \u0438\u0441\u043a\u0430\u043b\u0438",
    "menu-discover": "\u041e\u0431\u043d\u0430\u0440\u0443\u0436\u0438\u0442\u044c",
    "menu-library": "\u0412\u0430\u0448\u0430 \u0431\u0438\u0431\u043b\u0438\u043e\u0442\u0435\u043a\u0430",
    "menu-spotify": "Spotify",
    "menu-apple-music": "Apple Music",
    "menu-radio": "\u0420\u0430\u0434\u0438\u043e",
    "menu-podcasts": "\u041f\u043e\u0434\u043a\u0430\u0441\u0442\u044b",
    "menu-recommendations": "\u0440\u0435\u043a\u043e\u043c\u0435\u043d\u0434\u0430\u0446\u0438\u0438",
    "button-sonos-add": "\u0414\u043e\u0431\u0430\u0432\u0438\u0442\u044c Sonos",
    "button-sonos-remove": "\u0423\u0434\u0430\u043b\u0438\u0442\u044c Sonos",
    "button-stream": "\u041d\u0430\u0447\u0430\u043b\u043e \u0438\u0433\u0440\u044b",
    "button-stream-playlist": "\u0418\u0433\u0440\u0430\u0442\u044c \u043d\u0430 Sonos ...",
    "button-connect-services": "\u041f\u043e\u0434\u043a\u043b\u044e\u0447\u0438\u0442\u0435 \u0443\u0441\u043b\u0443\u0433\u0438",
    "sonos-control-center": "\u0421\u043e\u043d\u043e\u0441 \u041a\u043e\u043d\u0442\u0440\u043e\u043b\u044c \u0426\u0435\u043d\u0442\u0440\u0435",
    "sonos-control-center-text": "\u0426\u0435\u043d\u0442\u0440 \u0443\u043f\u0440\u0430\u0432\u043b\u0435\u043d\u0438\u044f Sonos \u043f\u043e\u0437\u0432\u043e\u043b\u044f\u0435\u0442 \u043f\u043e\u0434\u043a\u043b\u044e\u0447\u0430\u0442\u044c \u0438 \u043e\u0442\u043a\u043b\u044e\u0447\u0430\u0442\u044c \u0432\u0430\u0448\u0438 \u0443\u0441\u0442\u0440\u043e\u0439\u0441\u0442\u0432\u0430, \u043a\u0430\u043a \u0432\u0430\u043c \u043d\u0440\u0430\u0432\u0438\u0442\u0441\u044f. \u041f\u0440\u043e\u0441\u0442\u043e \u043f\u0435\u0440\u0435\u0442\u044f\u043d\u0438\u0442\u0435 \u0443\u0441\u0442\u0440\u043e\u0439\u0441\u0442\u0432\u043e \u0432 \u043d\u0443\u0436\u043d\u043e\u0435 \u043f\u043e\u043b\u043e\u0436\u0435\u043d\u0438\u0435.",
    "sonos-model-one-sl": "Sonos One SL",
    "sonos-model-one": "Sonos One",
    "sonos-model-five": "Sonos Five"
  }
]